vinzy_automl/__init__.py
vinzy_automl/automl.py
vinzy_automl-1.0.0.dist-info/licenses/LICENSE
vinzy_automl-1.0.0.dist-info/METADATA
vinzy_automl-1.0.0.dist-info/WHEEL
vinzy_automl-1.0.0.dist-info/top_level.txt
vinzy_automl-1.0.0.dist-info/RECORD
