Metadata-Version: 2.4
Name: vinzy_automl
Version: 1.0.0
Summary: Automated Machine Learning package
Home-page: https://github.com/vinayak-97/vinzy_automl
Author: Vinayak Bhosale
License: MIT
Project-URL: Homepage, https://github.com/vinayak-97/vinzy_automl
Requires-Python: >=3.7
License-File: LICENSE
Requires-Dist: numpy>=1.20.0
Requires-Dist: pandas>=1.0.0
Requires-Dist: scikit-learn>=1.0.0
Requires-Dist: matplotlib>=3.5.0
Provides-Extra: full
Requires-Dist: xgboost>=1.5.0; extra == "full"
Requires-Dist: lightgbm>=3.3.0; extra == "full"
Requires-Dist: catboost>=1.0.0; extra == "full"
Dynamic: home-page
Dynamic: license-file
Dynamic: requires-python
